agent_heaven-0.9.2.dist-info/licenses/LICENSE
ahvn/__init__.py
ahvn/version.py
ahvn/adapter/__init__.py
ahvn/adapter/base.py
ahvn/adapter/db.py
ahvn/adapter/mdb.py
ahvn/adapter/vdb.py
ahvn/agent/__init__.py
ahvn/agent/base.py
ahvn/agent/conv_agent.py
ahvn/agent/oracle_agent.py
ahvn/agent/submit_agent.py
ahvn/cache/__init__.py
ahvn/cache/base.py
ahvn/cache/callback_cache.py
ahvn/cache/db_cache.py
ahvn/cache/disk_cache.py
ahvn/cache/in_mem_cache.py
ahvn/cache/json_cache.py
ahvn/cache/mongo_cache.py
ahvn/cache/no_cache.py
ahvn/cli/__init__.py
ahvn/cli/ahvn.py
ahvn/cli/babel_cli.py
ahvn/cli/chat_cli.py
ahvn/cli/config_cli.py
ahvn/cli/repo_cli.py
ahvn/cli/utils.py
ahvn/klbase/__init__.py
ahvn/klbase/base.py
ahvn/klengine/__init__.py
ahvn/klengine/base.py
ahvn/klengine/daac_engine.py
ahvn/klengine/facet_engine.py
ahvn/klengine/mongo_engine.py
ahvn/klengine/scan_engine.py
ahvn/klengine/vector_engine.py
ahvn/klstore/__init__.py
ahvn/klstore/base.py
ahvn/klstore/cache_store.py
ahvn/klstore/cascade_store.py
ahvn/klstore/db_store.py
ahvn/klstore/mdb_store.py
ahvn/klstore/vdb_store.py
ahvn/llm/__init__.py
ahvn/llm/base.py
ahvn/llm/llm_utils.py
ahvn/resources/__init__.py
ahvn/resources/ahvn_kb.py
ahvn/resources/exps/gen_enum_synonyms/script.py
ahvn/resources/exps/gen_field_synonyms/script.py
ahvn/resources/prompts/system/filters/json_repr.py
ahvn/resources/prompts/system/filters/omission_list.py
ahvn/tool/__init__.py
ahvn/tool/base.py
ahvn/tool/mixin.py
ahvn/tool/builtins/__init__.py
ahvn/tool/builtins/db/__init__.py
ahvn/tool/builtins/db/exec_sql.py
ahvn/tool/builtins/db/info.py
ahvn/ukf/__init__.py
ahvn/ukf/base.py
ahvn/ukf/registry.py
ahvn/ukf/types.py
ahvn/ukf/ukf_utils.py
ahvn/ukf/templates/__init__.py
ahvn/ukf/templates/basic/__init__.py
ahvn/ukf/templates/basic/document.py
ahvn/ukf/templates/basic/dummy.py
ahvn/ukf/templates/basic/experience.py
ahvn/ukf/templates/basic/knowledge.py
ahvn/ukf/templates/basic/prompt.py
ahvn/ukf/templates/basic/resource.py
ahvn/ukf/templates/basic/template.py
agent_heaven-0.9.2.dist-info/METADATA
agent_heaven-0.9.2.dist-info/WHEEL
agent_heaven-0.9.2.dist-info/entry_points.txt
agent_heaven-0.9.2.dist-info/top_level.txt
agent_heaven-0.9.2.dist-info/RECORD
