Metadata-Version: 2.4
Name: agent-heaven
Version: 0.9.2
Summary: AgentHeaven: Ask not what your agents can do for you, ask what you can do for your agents.
Author-email: RubikSQL Team <chenzui1@huawei.com>
License: Sustainable Use License
Project-URL: Homepage, https://github.com/orgs/RubikSQL
Project-URL: Documentation, https://rubiksql.github.io/AgentHeaven-docs
Project-URL: Repository, https://github.com/RubikSQL/AgentHeaven
Project-URL: Bug Tracker, https://github.com/RubikSQL/AgentHeaven/issues
Keywords: agent,ai,heaven,ahvn
Classifier: Development Status :: 3 - Alpha
Classifier: Intended Audience :: Developers
Classifier: Topic :: Scientific/Engineering :: Artificial Intelligence
Classifier: Programming Language :: Python :: 3
Classifier: Operating System :: OS Independent
Requires-Python: <3.14,>=3.10
License-File: LICENSE
Requires-Dist: babel>=2.17.0
Requires-Dist: click>=8.0
Requires-Dist: cloudpickle>=2.0
Requires-Dist: dill>=0.3
Requires-Dist: diskcache>=5.0
Requires-Dist: docstring-parser>=0.15
Requires-Dist: isodate>=0.6
Requires-Dist: Jinja2>=3.0
Requires-Dist: litellm>=1.0
Requires-Dist: openai>=1.0
Requires-Dist: pandas>=2.3.3
Requires-Dist: polib>=1.2.0
Requires-Dist: prettytable>=3.17.0
Requires-Dist: pydantic>=2.0
Requires-Dist: pyyaml>=6.0
Requires-Dist: requests>=2.28
Requires-Dist: tenacity>=8.0
Requires-Dist: termcolor>=2.0
Requires-Dist: prompt_toolkit>=3.0
Provides-Extra: exp
Requires-Dist: asyncpg; extra == "exp"
Requires-Dist: chromadb; extra == "exp"
Requires-Dist: duckdb-engine; extra == "exp"
Requires-Dist: duckdb==1.3.2; extra == "exp"
Requires-Dist: fastmcp; extra == "exp"
Requires-Dist: gdown; extra == "exp"
Requires-Dist: ipykernel; extra == "exp"
Requires-Dist: lancedb; extra == "exp"
Requires-Dist: llama-index-core>=0.10; extra == "exp"
Requires-Dist: llama-index-tools-neo4j; extra == "exp"
Requires-Dist: llama-index-vector-stores-chroma; extra == "exp"
Requires-Dist: llama-index-vector-stores-lancedb; extra == "exp"
Requires-Dist: llama-index-vector-stores-milvus; extra == "exp"
Requires-Dist: llama-index-vector-stores-postgres; extra == "exp"
Requires-Dist: ollama; extra == "exp"
Requires-Dist: prettytable>=3.0; extra == "exp"
Requires-Dist: prompt_toolkit; extra == "exp"
Requires-Dist: psycopg2-binary; extra == "exp"
Requires-Dist: pyahocorasick; extra == "exp"
Requires-Dist: pyarrow; extra == "exp"
Requires-Dist: pymilvus==2.6.3; extra == "exp"
Requires-Dist: pymongo; extra == "exp"
Requires-Dist: pymongo>=4.0; extra == "exp"
Requires-Dist: pymysql; extra == "exp"
Requires-Dist: pyodbc; extra == "exp"
Requires-Dist: spacy; extra == "exp"
Requires-Dist: sqlalchemy>=2.0; extra == "exp"
Requires-Dist: sqlglot>=20.0; extra == "exp"
Provides-Extra: dev
Requires-Dist: furo>=2023.9.10; extra == "dev"
Requires-Dist: myst-parser>=2.0.0; extra == "dev"
Requires-Dist: sphinx-autodoc-typehints>=1.25.0; extra == "dev"
Requires-Dist: sphinx-copybutton>=0.5.2; extra == "dev"
Requires-Dist: sphinx-intl>=2.1.0; extra == "dev"
Requires-Dist: sphinx-rtd-theme>=2.0.0; extra == "dev"
Requires-Dist: sphinx-tabs>=3.4.1; extra == "dev"
Requires-Dist: sphinx>=7.0.0; extra == "dev"
Requires-Dist: sphinxcontrib-mermaid>=0.9.2; extra == "dev"
Requires-Dist: nbsphinx>=0.9.1; extra == "dev"
Requires-Dist: sphinx-autobuild>=2021.3.14; extra == "dev"
Requires-Dist: sphinx-design>=0.5.0; extra == "dev"
Requires-Dist: sphinx-external-toc>=1.0.1; extra == "dev"
Requires-Dist: sphinx-gallery>=0.14.0; extra == "dev"
Requires-Dist: sphinxext-opengraph>=0.9.0; extra == "dev"
Requires-Dist: doc8>=1.1.1; extra == "dev"
Requires-Dist: linkchecker>=10.2.1; extra == "dev"
Requires-Dist: rstcheck>=6.2.0; extra == "dev"
Requires-Dist: black[jupyter]; extra == "dev"
Requires-Dist: flake8>=7.1.1; extra == "dev"
Requires-Dist: pre-commit>=3.8.0; extra == "dev"
Requires-Dist: pytest-asyncio>=0.24.0; extra == "dev"
Requires-Dist: pytest>=8.4.1; extra == "dev"
Dynamic: license-file
